{
    "Brand": [
        {
            "Id": "4v8pdkyg",
            "Name": "Cadillac",
            "Selected": false
        },
        {
            "Id": "9vtpdkyg",
            "Name": "Chevrolet",
            "Selected": false
        },
        {
            "Id": "xvqpdkyg",
            "Name": "Dodge",
            "Selected": false
        },
        {
            "Id": "cvmpdkyg",
            "Name": "Ford",
            "Selected": false
        },
        {
            "Id": "dvspdkyg",
            "Name": "Jeep",
            "Selected": false
        },
        {
            "Id": "gvt3dkyg",
            "Name": "Mercedes-Benz",
            "Selected": false
        },
        {
            "Id": "kvj3dkyg",
            "Name": "Porsche",
            "Selected": false
        }
    ],
    "Body": [
        {
            "Id": "rvppdkyg",
            "Name": "Personbilar",
            "Selected": false
        },
        {
            "Id": "pv7pdkyg",
            "Name": "Transportbilar",
            "Selected": false
        },
        {
            "Id": "sv3pdkyg",
            "Name": "Husvagnar",
            "Selected": false
        },
        {
            "Id": "3v2pdkyg",
            "Name": "Husbilar",
            "Selected": false
        },
        {
            "Id": "vvipdkyg",
            "Name": "Motorcyklar",
            "Selected": false
        },
        {
            "Id": "ivfpdkyg",
            "Name": "Mopeder",
            "Selected": false
        }
    ],
    "Year": [
        {
            "Id": "3v2vakyg",
            "Name": "2021",
            "Selected": false
        },
        {
            "Id": "pv7vakyg",
            "Name": "2020",
            "Selected": false
        },
        {
            "Id": "vvivakyg",
            "Name": "2019",
            "Selected": false
        },
        {
            "Id": "sv3vakyg",
            "Name": "2018",
            "Selected": false
        },
        {
            "Id": "rvpvakyg",
            "Name": "2017",
            "Selected": false
        },
        {
            "Id": "avvvakyg",
            "Name": "2016",
            "Selected": false
        },
        {
            "Id": "bvssakyg",
            "Name": "2015",
            "Selected": false
        },
        {
            "Id": "zvrsakyg",
            "Name": "2014",
            "Selected": false
        },
        {
            "Id": "uvasakyg",
            "Name": "2013",
            "Selected": false
        },
        {
            "Id": "yvdsakyg",
            "Name": "2012",
            "Selected": false
        },
        {
            "Id": "jvbsakyg",
            "Name": "2011",
            "Selected": false
        },
        {
            "Id": "mvzsakyg",
            "Name": "2010",
            "Selected": false
        },
        {
            "Id": "kvusakyg",
            "Name": "2009",
            "Selected": false
        },
        {
            "Id": "hvysakyg",
            "Name": "2008",
            "Selected": false
        },
        {
            "Id": "cvjsakyg",
            "Name": "2007",
            "Selected": false
        },
        {
            "Id": "qvmsakyg",
            "Name": "2006",
            "Selected": false
        },
        {
            "Id": "evksakyg",
            "Name": "2005",
            "Selected": false
        },
        {
            "Id": "6vhsakyg",
            "Name": "2004",
            "Selected": false
        },
        {
            "Id": "xvcsakyg",
            "Name": "2003",
            "Selected": false
        },
        {
            "Id": "5vqsakyg",
            "Name": "2002",
            "Selected": false
        },
        {
            "Id": "nvesakyg",
            "Name": "2001",
            "Selected": false
        },
        {
            "Id": "wv6sakyg",
            "Name": "2000",
            "Selected": false
        },
        {
            "Id": "tvxsakyg",
            "Name": "1999",
            "Selected": false
        },
        {
            "Id": "8v5sakyg",
            "Name": "1998",
            "Selected": false
        },
        {
            "Id": "gvnsakyg",
            "Name": "1997",
            "Selected": false
        },
        {
            "Id": "9vwsakyg",
            "Name": "1996",
            "Selected": false
        },
        {
            "Id": "4vtsakyg",
            "Name": "1995",
            "Selected": false
        }
    ],
    "Fuel": [],
    "Gearbox": []
}
